tests/__init__.py
tests/test_client.py
tsf_sh/__init__.py
tsf_sh/client.py
tsf_sh/exceptions.py
tsf_sh/models.py
tsf_sh-1.0.1.dist-info/METADATA
tsf_sh-1.0.1.dist-info/WHEEL
tsf_sh-1.0.1.dist-info/top_level.txt
tsf_sh-1.0.1.dist-info/RECORD
